easytranslator/__init__.py
easytranslator/main.py
easytranslator/manual_mapping.py
easytranslator/settings.py
easytranslator-2024.6.20.dist-info/METADATA
easytranslator-2024.6.20.dist-info/WHEEL
easytranslator-2024.6.20.dist-info/licenses/LICENSE
easytranslator-2024.6.20.dist-info/RECORD
