Metadata-Version: 2.3
Name: easytranslator
Version: 2024.6.20
Summary: A Python package for reliable text translation using multiple free engines with automatic failover.
Project-URL: Homepage, https://github.com/versun/easytranslator
Project-URL: Repository, https://github.com/versun/easytranslator.git
Project-URL: Issues, https://github.com/versun/easytranslator/issues
Author-email: Versun <easytranslator@versun.me>
License: GPL-3.0 license
License-File: LICENSE
Classifier: Environment :: Web Environment
Classifier: Intended Audience :: Developers
Classifier: Operating System :: OS Independent
Classifier: Programming Language :: Python
Classifier: Programming Language :: Python :: 3
Classifier: Programming Language :: Python :: 3 :: Only
Classifier: Programming Language :: Python :: 3.10
Classifier: Programming Language :: Python :: 3.11
Classifier: Programming Language :: Python :: 3.12
Classifier: Topic :: Software Development :: Libraries :: Python Modules
Requires-Python: >=3.10
Requires-Dist: translators
